setup.py
tools_wzy/__init__.py
tools_wzy/node_coverage.py
tools_wzy/yolo_need.py
tools_wzy.egg-info/PKG-INFO
tools_wzy.egg-info/SOURCES.txt
tools_wzy.egg-info/dependency_links.txt
tools_wzy.egg-info/requires.txt
tools_wzy.egg-info/top_level.txt