Metadata-Version: 2.1
Name: tools-wzy
Version: 0.0.3
Summary: Some python tools for work from Zhiyuan
Home-page: https://gitee.com/Zhiyuan_WZY
Author: Zhiyuan Wang
Author-email: 2073834696@qq.com
License: MIT Licence
Keywords: pip,tools_wzy
Platform: any
